songpy/__init__.py
songpy/generator.py
songpy/song.py
songpy/music/__init__.py
songpy/music/chord.py
songpy/music/interval.py
songpy/music/note.py
songpy/utils/__init__.py
songpy/utils/filters.py
songpy/utils/formatter.py
songpy/utils/parser.py
songpy/utils/transpose.py
songpy-1.0.0.dist-info/METADATA
songpy-1.0.0.dist-info/WHEEL
songpy-1.0.0.dist-info/top_level.txt
songpy-1.0.0.dist-info/RECORD
