Metadata-Version: 2.1
Name: songpy
Version: 1.0.0
Summary: Package with objects representing objects of musical notation
Author: Karol Ważny
